.run.me
AUTHORS
ChangeLog
Makefile
README.md
VERSION
Vagrantfile
build-requirements.txt
configure
requirements.txt
setup.cfg
setup.py
test.py
.readmeimg/asset-card.svg
.readmeimg/sysarch.png
.sphinx/Makefile
.sphinx/conf.py
.sphinx/index.rst
.sphinx/lmaps.core.rst
.sphinx/lmaps.plugins.rst
.sphinx/lmaps.rst
.sphinx/make.bat
.sphinx/_build/doctrees/environment.pickle
.sphinx/_build/doctrees/index.doctree
.sphinx/_build/doctrees/lmaps.core.doctree
.sphinx/_build/doctrees/lmaps.doctree
.sphinx/_build/doctrees/lmaps.plugins.doctree
.sphinx/_build/html/.buildinfo
.sphinx/_build/html/genindex.html
.sphinx/_build/html/index.html
.sphinx/_build/html/lmaps.core.html
.sphinx/_build/html/lmaps.html
.sphinx/_build/html/lmaps.plugins.html
.sphinx/_build/html/objects.inv
.sphinx/_build/html/py-modindex.html
.sphinx/_build/html/search.html
.sphinx/_build/html/searchindex.js
.sphinx/_build/html/_sources/index.rst.txt
.sphinx/_build/html/_sources/lmaps.core.rst.txt
.sphinx/_build/html/_sources/lmaps.plugins.rst.txt
.sphinx/_build/html/_sources/lmaps.rst.txt
.sphinx/_build/html/_static/ajax-loader.gif
.sphinx/_build/html/_static/alabaster.css
.sphinx/_build/html/_static/basic.css
.sphinx/_build/html/_static/comment-bright.png
.sphinx/_build/html/_static/comment-close.png
.sphinx/_build/html/_static/comment.png
.sphinx/_build/html/_static/custom.css
.sphinx/_build/html/_static/doctools.js
.sphinx/_build/html/_static/documentation_options.js
.sphinx/_build/html/_static/down-pressed.png
.sphinx/_build/html/_static/down.png
.sphinx/_build/html/_static/file.png
.sphinx/_build/html/_static/jquery-3.2.1.js
.sphinx/_build/html/_static/jquery.js
.sphinx/_build/html/_static/minus.png
.sphinx/_build/html/_static/plus.png
.sphinx/_build/html/_static/pygments.css
.sphinx/_build/html/_static/searchtools.js
.sphinx/_build/html/_static/underscore-1.3.1.js
.sphinx/_build/html/_static/underscore.js
.sphinx/_build/html/_static/up-pressed.png
.sphinx/_build/html/_static/up.png
lmaps.egg-info/PKG-INFO
lmaps.egg-info/SOURCES.txt
lmaps.egg-info/dependency_links.txt
lmaps.egg-info/entry_points.txt
lmaps.egg-info/not-zip-safe
lmaps.egg-info/pbr.json
lmaps.egg-info/requires.txt
lmaps.egg-info/top_level.txt
