Metadata-Version: 1.1
Name: lmaps
Version: 1.1.0
Summary: Lightweight Management and Provisioning Service
Home-page: https://josiahkerley.github.io/python-lmaps/
Author: Josiah Kerley
Author-email: josiahkerley@gmail.com
License: UNKNOWN
Platform: UNKNOWN
Classifier: Operating System :: OS Independent
